boilerplate_tools/__init__.py
boilerplate_tools/src/__init__.py
boilerplate_tools/src/utils/__init__.py
boilerplate_tools/src/utils/config.py
boilerplate_tools/src/utils/json_io.py
boilerplate_tools/src/utils/path_handler.py
boilerplate_tools/src/utils/smart_format.py
bolerplate_tools-0.1.2.dist-info/METADATA
bolerplate_tools-0.1.2.dist-info/WHEEL
bolerplate_tools-0.1.2.dist-info/top_level.txt
bolerplate_tools-0.1.2.dist-info/RECORD
