Metadata-Version: 2.4
Name: bolerplate_tools
Version: 0.1.2
Summary: A set of helper functions
Home-page: https://github.com/RodionfromHSE/custom_python_tools.git
Author: Rodion Khvorostov
Author-email: rodion.khvorostov@jetbrains.com
Requires-Python: >=3.10
Requires-Dist: omegaconf
Dynamic: author
Dynamic: author-email
Dynamic: description
Dynamic: description-content-type
Dynamic: home-page
Dynamic: requires-dist
Dynamic: requires-python
Dynamic: summary
